odoo/addons/kpi_dashboard_bokeh/README.rst
odoo/addons/kpi_dashboard_bokeh/__init__.py
odoo/addons/kpi_dashboard_bokeh/__manifest__.py
odoo/addons/kpi_dashboard_bokeh/demo/demo_dashboard.xml
odoo/addons/kpi_dashboard_bokeh/i18n/kpi_dashboard_bokeh.pot
odoo/addons/kpi_dashboard_bokeh/models/__init__.py
odoo/addons/kpi_dashboard_bokeh/models/kpi_kpi.py
odoo/addons/kpi_dashboard_bokeh/readme/CONFIGURE.rst
odoo/addons/kpi_dashboard_bokeh/readme/CONTRIBUTORS.rst
odoo/addons/kpi_dashboard_bokeh/readme/DESCRIPTION.rst
odoo/addons/kpi_dashboard_bokeh/static/description/icon.png
odoo/addons/kpi_dashboard_bokeh/static/description/index.html
odoo/addons/kpi_dashboard_bokeh/static/src/js/bokeh_widget.js
odoo/addons/kpi_dashboard_bokeh/static/src/xml/dashboard.xml
odoo/addons/kpi_dashboard_bokeh/views/webclient_templates.xml
odoo12_addon_kpi_dashboard_bokeh-12.0.1.0.1.dist-info/METADATA
odoo12_addon_kpi_dashboard_bokeh-12.0.1.0.1.dist-info/WHEEL
odoo12_addon_kpi_dashboard_bokeh-12.0.1.0.1.dist-info/top_level.txt
odoo12_addon_kpi_dashboard_bokeh-12.0.1.0.1.dist-info/RECORD
